pyzora/__init__.py
pyzora/child_behaviour_tools.py
pyzora/enums.py
pyzora/exceptions.py
pyzora/game_secret.py
pyzora/memory_secret.py
pyzora/ring_secret.py
pyzora/ring_types.py
pyzora/secret.py
pyzora-1.0.0.dist-info/LICENSE
pyzora-1.0.0.dist-info/METADATA
pyzora-1.0.0.dist-info/WHEEL
pyzora-1.0.0.dist-info/top_level.txt
pyzora-1.0.0.dist-info/RECORD
