Metadata-Version: 2.1
Name: pyzora
Version: 1.0.0
Summary: Python library to help parsing secrets from Zelda OoS/OoA
Author: fortwoone
Project-URL: Homepage, https://github.com/fortwoone/pyzora
Project-URL: Issues, https://github.com/fortwoone/pyzora/issues
Classifier: Programming Language :: Python :: 3
Classifier: License :: OSI Approved :: GNU General Public License (GPL)
Classifier: Operating System :: OS Independent
Requires-Python: >=3.10
License-File: LICENSE
